info_ut/__init__.py
info_ut/feed/__init__.py
info_ut/feed/feed.py
info_ut/feed/feed_item.py
info_ut/post.py
info_ut/utils.py
info_ut-0.1.4.dist-info/LICENSE
info_ut-0.1.4.dist-info/WHEEL
info_ut-0.1.4.dist-info/METADATA
info_ut-0.1.4.dist-info/RECORD
