Metadata-Version: 2.1
Name: info-ut
Version: 0.1.4
Summary: Modul python untuk medapatkan informasi terbaru dari website Universitas Terbuka
Home-page: https://github.com/UnivTerbuka/info-ut
License: GPL-3.0-only
Author: hexatester
Author-email: hexatester@protonmail.com
Requires-Python: >=3.8,<4.0
Classifier: Development Status :: 4 - Beta
Classifier: Intended Audience :: Developers
Classifier: License :: OSI Approved :: GNU General Public License v3 (GPLv3)
Classifier: Operating System :: OS Independent
Classifier: Programming Language :: Python
Classifier: Programming Language :: Python :: 3
Classifier: Programming Language :: Python :: 3.8
Classifier: Programming Language :: Python :: 3.9
Classifier: Programming Language :: Python :: 3.10
Classifier: Programming Language :: Python :: 3.8
Classifier: Programming Language :: Python :: 3.9
Classifier: Topic :: Software Development :: Libraries :: Python Modules
Requires-Dist: attrs (>=21.0.0,<23.0.0)
Requires-Dist: beautifulsoup4 (>=4.11.1,<5.0.0)
Requires-Dist: feedparser (>=6.0.10,<7.0.0)
Requires-Dist: requests (>=2.28.1,<3.0.0)
Project-URL: Repository, https://github.com/UnivTerbuka/info-ut
